{
    "schedule_key": 7519,
    "date": {
        "season": "2021-22",
        "month": "11.06",
        "week": "[SAT]",
        "setsu": "第6節",
        "time": "14:05 TIP OFF"
    },
    "place": {
        "stadium": "よつ葉アリーナ十勝",
        "attendance": "1468人"
    },
    "referee": {
        "first": "久保 裕紀",
        "second": "小澤 勤",
        "crew": "一色 渉"
    },
    "team": {
        "home": "レバンガ北海道",
        "away": "宇都宮ブレックス"
    },
    "score": {
        "home": "70",
        "away": "93"
    }
}