{
    "schedule_key": 5059,
    "date": {
        "season": "2019-20",
        "month": "2.09",
        "week": "[SUN]",
        "setsu": "第22節",
        "time": "14:00 TIP OFF"
    },
    "place": {
        "stadium": "照葉積水ハウスアリーナ",
        "attendance": "2702人"
    },
    "referee": {
        "first": "蒲健一",
        "second": "岩木太郎",
        "crew": "高野杏実"
    },
    "team": {
        "home": "ライジングゼファー福岡",
        "away": "熊本ヴォルターズ"
    },
    "score": {
        "home": "86",
        "away": "93"
    }
}