{
    "schedule_key": 7072,
    "date": {
        "season": "2021-22",
        "month": "11.13",
        "week": null,
        "setsu": "レギュラーシーズン/岐阜スゥープスvs岩手ビッグブルズ",
        "time": "18:00 TIP OFF"
    },
    "place": {
        "stadium": "OKBぎふ清流アリーナ",
        "attendance": "525人"
    },
    "referee": {
        "first": "山内正隆",
        "second": "田中優志",
        "crew": "上西星太"
    },
    "team": {
        "home": "岐阜スゥープス",
        "away": "岩手ビッグブルズ"
    },
    "score": {
        "home": "68",
        "away": "81"
    }
}