{
    "schedule_key": 1762,
    "date": {
        "season": "2017-18",
        "month": "12.16",
        "week": "[Sat]",
        "setsu": "第12節",
        "time": "15:05 TIP OFF"
    },
    "place": {
        "stadium": "船橋アリーナ",
        "attendance": "5189人"
    },
    "referee": {
        "first": "加藤誉樹",
        "second": "久米克弥",
        "crew": "阿部聖"
    },
    "team": {
        "home": "千葉ジェッツ",
        "away": "川崎ブレイブサンダース"
    },
    "score": {
        "home": "79",
        "away": "57"
    }
}