{
    "schedule_key": 7338,
    "date": {
        "season": "2021-22",
        "month": "3.26",
        "week": null,
        "setsu": null,
        "time": "15:00 TIP OFF"
    },
    "place": {
        "stadium": "OKBぎふ清流アリーナ",
        "attendance": "604人"
    },
    "referee": {
        "first": "井出啓太",
        "second": "林大貴",
        "crew": "山田 隆介"
    },
    "team": {
        "home": "岐阜スゥープス",
        "away": "アイシン アレイオンズ"
    },
    "score": {
        "home": "81",
        "away": "72"
    }
}