{
    "schedule_key": 4198,
    "date": {
        "season": "2019-20",
        "month": "10.19",
        "week": "[SAT]",
        "setsu": "第4節",
        "time": "16:05 TIP OFF"
    },
    "place": {
        "stadium": "船橋アリーナ",
        "attendance": "4590人"
    },
    "referee": {
        "first": "平出剛",
        "second": "小澤勤",
        "crew": "岩井 遥河"
    },
    "team": {
        "home": "千葉ジェッツ",
        "away": "川崎ブレイブサンダース"
    },
    "score": {
        "home": "73",
        "away": "83"
    }
}