{
    "schedule_key": 2958,
    "date": {
        "season": "2018-19",
        "month": "4.06",
        "week": null,
        "setsu": null,
        "time": "18:30 TIP OFF"
    },
    "place": {
        "stadium": "板橋区立小豆沢体育館",
        "attendance": "922人"
    },
    "referee": {
        "first": "嶋崎貴",
        "second": "前花直哉",
        "crew": "一色渉"
    },
    "team": {
        "home": "東京エクセレンス",
        "away": "大塚商会越谷アルファーズ"
    },
    "score": {
        "home": "90",
        "away": "87"
    }
}