{
    "schedule_key": 1847,
    "date": {
        "season": "2017-18",
        "month": "1.26",
        "week": "[Fri]",
        "setsu": "第17節",
        "time": "19:05 TIP OFF"
    },
    "place": {
        "stadium": "川崎市とどろきアリーナ",
        "attendance": "2940人"
    },
    "referee": {
        "first": "漆間大吾",
        "second": "東祐二",
        "crew": "細田知宏"
    },
    "team": {
        "home": "川崎ブレイブサンダース",
        "away": "千葉ジェッツ"
    },
    "score": {
        "home": "87",
        "away": "80"
    }
}