{
    "schedule_key": 5257,
    "date": {
        "season": "2019-2020",
        "month": "9.16",
        "week": null,
        "setsu": null,
        "time": "14:00 TIP OFF"
    },
    "place": {
        "stadium": "シティホールプラザ　アオーレ長岡",
        "attendance": ""
    },
    "referee": {
        "first": "玉木彰治",
        "second": "石田祐二",
        "crew": "北島寛臣"
    },
    "team": {
        "home": "金沢武士団",
        "away": "信州ブレイブウォリアーズ"
    },
    "score": {
        "home": "56",
        "away": "99"
    }
}