{
    "schedule_key": 572,
    "date": {
        "season": "2016-17",
        "month": "10.02",
        "week": "[Sun]",
        "setsu": "第2節",
        "time": "14:00 TIP OFF"
    },
    "place": {
        "stadium": "大田区総合体育館",
        "attendance": "861人"
    },
    "referee": {
        "first": "飯尾勝紀",
        "second": "大野 太裕",
        "crew": "漆間 大吾"
    },
    "team": {
        "home": "アースフレンズ東京Z",
        "away": "Fイーグルス名古屋"
    },
    "score": {
        "home": "59",
        "away": "75"
    }
}