{
    "schedule_key": 5844,
    "date": {
        "season": "2020-21",
        "month": "6.05",
        "week": null,
        "setsu": "レギュラーシーズン/岐阜スゥープスvs東京八王子ビートレインズ",
        "time": "17:00 TIP OFF"
    },
    "place": {
        "stadium": "OKBぎふ清流アリーナ",
        "attendance": "706人"
    },
    "referee": {
        "first": "中川行臣",
        "second": "加藤昌樹",
        "crew": "岩城和利"
    },
    "team": {
        "home": "岐阜スゥープス",
        "away": "東京八王子ビートレインズ"
    },
    "score": {
        "home": "78",
        "away": "70"
    }
}