{
    "schedule_key": 3080,
    "date": {
        "season": "2018-19",
        "month": "11.03",
        "week": "[SAT]",
        "setsu": "第7節",
        "time": "15:05 TIP OFF"
    },
    "place": {
        "stadium": "船橋アリーナ",
        "attendance": "4831人"
    },
    "referee": {
        "first": "小澤勤",
        "second": "阿部聖",
        "crew": "東條輝正"
    },
    "team": {
        "home": "千葉ジェッツ",
        "away": "サンロッカーズ渋谷"
    },
    "score": {
        "home": "85",
        "away": "83"
    }
}