{
    "schedule_key": 5967,
    "date": {
        "season": "2020-21",
        "month": "11.08",
        "week": "[SUN]",
        "setsu": "第7節",
        "time": "13:05 TIP OFF"
    },
    "place": {
        "stadium": "シティホールプラザアオーレ長岡",
        "attendance": "1834人"
    },
    "referee": {
        "first": "久保 裕紀",
        "second": "芳賀 聡",
        "crew": "眞榮喜 工"
    },
    "team": {
        "home": "新潟アルビレックスBB",
        "away": "宇都宮ブレックス"
    },
    "score": {
        "home": "67",
        "away": "85"
    }
}