{
    "schedule_key": 476,
    "date": {
        "season": "2016-17",
        "month": "4.15",
        "week": "[Sat]",
        "setsu": "第28節",
        "time": "17:00 TIP OFF"
    },
    "place": {
        "stadium": "国立代々木競技場第二体育館",
        "attendance": "3206人"
    },
    "referee": {
        "first": "相原伸康",
        "second": "久米克弥",
        "crew": "有澤重行"
    },
    "team": {
        "home": "アルバルク東京",
        "away": "千葉ジェッツ"
    },
    "score": {
        "home": "81",
        "away": "87"
    }
}