{
    "schedule_key": 1183,
    "date": {
        "season": "2016-17",
        "month": "1.14",
        "week": null,
        "setsu": "レギュラーシーズン/埼玉ブロンコスvs東京八王子トレインズ",
        "time": "18:00 TIP OFF"
    },
    "place": {
        "stadium": "所沢市民体育館",
        "attendance": "561人"
    },
    "referee": {
        "first": "平林達哉",
        "second": "和嶋陽一",
        "crew": "一色渉"
    },
    "team": {
        "home": "埼玉ブロンコス",
        "away": "東京八王子トレインズ"
    },
    "score": {
        "home": "87",
        "away": "91"
    }
}