{
    "schedule_key": 5305,
    "date": {
        "season": "2019-20",
        "month": "10.12",
        "week": null,
        "setsu": null,
        "time": "11:00 TIP OFF"
    },
    "place": {
        "stadium": "アイシンAW体育館",
        "attendance": ""
    },
    "referee": {
        "first": "豊田 康平",
        "second": "山本雄大",
        "crew": "内野 翔太"
    },
    "team": {
        "home": "アイシン・エィ・ダブリュ アレイオンズ安城",
        "away": "東京サンレーヴス"
    },
    "score": {
        "home": "76",
        "away": "69"
    }
}