{
    "schedule_key": 7585,
    "date": {
        "season": "2021-22",
        "month": "12.05",
        "week": "[SUN]",
        "setsu": "第9節",
        "time": "14:05 TIP OFF"
    },
    "place": {
        "stadium": "ホワイトリング",
        "attendance": "3225人"
    },
    "referee": {
        "first": "伊藤 亮介",
        "second": "久米 克弥",
        "crew": "冨島 健司"
    },
    "team": {
        "home": "信州ブレイブウォリアーズ",
        "away": "宇都宮ブレックス"
    },
    "score": {
        "home": "61",
        "away": "83"
    }
}