{
    "schedule_key": 1093,
    "date": {
        "season": "2016-17",
        "month": "10.07",
        "week": "unknown",
        "setsu": "unknown",
        "time": "unknown"
    },
    "place": {
        "stadium": "飯塚第一体育館",
        "attendance": "525人"
    },
    "referee": {
        "first": "岩尾圭治",
        "second": "比嘉涼太",
        "crew": "勝原芳徳"
    },
    "team": {
        "home": "ライジングゼファーフクオカ",
        "away": "埼玉ブロンコス"
    },
    "score": {
        "home": "90",
        "away": "55"
    }
}