{
    "schedule_key": 3708,
    "date": {
        "season": "2018-19",
        "month": "12.09",
        "week": "[SUN]",
        "setsu": "第11節",
        "time": "13:30 TIP OFF"
    },
    "place": {
        "stadium": "島根県立浜山体育館（カミアリーナ）",
        "attendance": "2057人"
    },
    "referee": {
        "first": "守谷圭介",
        "second": "岩木太郎",
        "crew": "柳田 雅人"
    },
    "team": {
        "home": "島根スサノオマジック",
        "away": "仙台89ERS"
    },
    "score": {
        "home": "74",
        "away": "72"
    }
}